SDK/LOTR_SDK.py
SDK/__init__.py
SDK/test_all.py
Ty_Delargy_SDK-0.0.5.dist-info/LICENSE
Ty_Delargy_SDK-0.0.5.dist-info/METADATA
Ty_Delargy_SDK-0.0.5.dist-info/WHEEL
Ty_Delargy_SDK-0.0.5.dist-info/top_level.txt
Ty_Delargy_SDK-0.0.5.dist-info/RECORD
