Metadata-Version: 2.1
Name: Ty-Delargy-SDK
Version: 0.0.5
Home-page: https://github.com/tydelargy/Ty_Delargy-SDK
Author: Ty Delargy
Author-email: tjdelargy@gmail.com
Classifier: Programming Language :: Python :: 3
Classifier: License :: OSI Approved :: MIT License
Classifier: Operating System :: OS Independent
Requires-Python: >=3.11.0
License-File: LICENSE
Requires-Dist: pytest (>=7.2.2)
Requires-Dist: requests (>=2.28.2)
